.editorconfig
.gitignore
CHANGELOG.md
MANIFEST.in
Makefile
README.md
pyproject.toml
requirements-dev.txt
requirements-test.txt
setup.cfg
setup.py
tox.ini
.github/workflows/test.yml
gen/m68kops.c
src/cpu.c
src/cpu.h
src/cpu.pyx
src/m68k.pyx
src/mach.c
src/mach.pyx
src/mem.c
src/mem.h
src/mem.pyx
src/my_conf.h
src/pycpu.pyx
src/pymem.pyx
src/pytraps.pyx
src/traps.c
src/traps.h
src/traps.pyx
src/machine68k.egg-info/PKG-INFO
src/machine68k.egg-info/SOURCES.txt
src/machine68k.egg-info/dependency_links.txt
src/machine68k.egg-info/top_level.txt
src/musashi/Makefile
src/musashi/history.txt
src/musashi/m68k.h
src/musashi/m68k_in.c
src/musashi/m68kconf.h
src/musashi/m68kcpu.c
src/musashi/m68kcpu.h
src/musashi/m68kdasm.c
src/musashi/m68kfpu.c
src/musashi/m68kmake.c
src/musashi/m68kmmu.h
src/musashi/readme.txt
src/musashi/softfloat/README.txt
src/musashi/softfloat/mamesf.h
src/musashi/softfloat/milieu.h
src/musashi/softfloat/softfloat-macros
src/musashi/softfloat/softfloat-specialize
src/musashi/softfloat/softfloat.c
src/musashi/softfloat/softfloat.h
src/win/stdint.h
test/bench_machine.py
test/bench_traps.py
test/conftest.py
test/opcodes.py
test/pytest.ini
test/test_cpu.py
test/test_greenlet.py
test/test_machine.py
test/test_mem.py
test/test_traps.py