Metadata-Version: 2.4
Name: machine68k
Version: 0.4.1
Summary: A Cython binding for a m68k system emulator
Author-email: Christian Vogelgsang <chris@vogelgsang.org>
License-Expression: GPL-2.0-or-later
Keywords: m68k,musashi,machine68k,system emulator
Classifier: Development Status :: 4 - Beta
Classifier: Intended Audience :: Developers
Classifier: Programming Language :: Python
Classifier: Topic :: System :: Emulators
Requires-Python: >=3.9
